apcase
