Metadata-Version: 2.1
Name: apcase
Version: 0.0.4
Summary: itfeat
Home-page: http://www.itfeat.com
Author: YosonHao
Author-email: haoyuexing@gmail.com
License: MIT
Platform: UNKNOWN
Classifier: Programming Language :: Python :: 3
Classifier: License :: OSI Approved :: MIT License
Classifier: Operating System :: OS Independent
Requires-Python: >=3.6
